[
    {
        "id": 1,
        "name": "강유라",
        "present": false,
        "code": "",
        "timestamp": null,
        "password": "9272",
        "deleted_at": "2025-03-24 22:15:35"
    },
    {
        "id": 4,
        "name": "권혁규",
        "present": false,
        "code": "",
        "timestamp": null,
        "password": "6085",
        "deleted_at": "2025-03-24 22:15:35"
    },
    {
        "id": 11,
        "name": "김서영",
        "present": false,
        "code": "",
        "timestamp": null,
        "password": "8415",
        "deleted_at": "2025-03-24 22:15:35"
    },
    {
        "id": 19,
        "name": "김지환",
        "present": false,
        "code": "",
        "timestamp": null,
        "password": "4826",
        "deleted_at": "2025-03-24 22:15:35"
    },
    {
        "id": 32,
        "name": "안치욱",
        "present": false,
        "code": "",
        "timestamp": null,
        "password": "5321",
        "deleted_at": "2025-03-24 22:15:35"
    },
    {
        "id": 52,
        "name": "정우진",
        "present": false,
        "code": "",
        "timestamp": null,
        "password": "7175",
        "deleted_at": "2025-03-24 22:15:35"
    },
    {
        "id": 54,
        "name": "조효선",
        "present": false,
        "code": "",
        "timestamp": null,
        "password": "3107",
        "deleted_at": "2025-03-24 22:15:35"
    },
    {
        "id": 58,
        "name": "한재연",
        "present": false,
        "code": "",
        "timestamp": null,
        "password": "1764",
        "deleted_at": "2025-03-24 22:15:35"
    },
    {
        "id": 59,
        "name": "한혜진",
        "present": false,
        "code": "",
        "timestamp": null,
        "password": "9222",
        "deleted_at": "2025-03-24 22:15:35"
    },
    {
        "id": 61,
        "name": "홍현진",
        "present": false,
        "code": "",
        "timestamp": null,
        "password": "6950",
        "deleted_at": "2025-03-24 22:15:35"
    },
    {
        "id": 64,
        "name": "강서영",
        "present": false,
        "code": "",
        "timestamp": null,
        "password": "1665",
        "deleted_at": "2025-03-24 22:15:35"
    },
    {
        "id": 69,
        "name": "김동현",
        "present": false,
        "code": "",
        "timestamp": null,
        "password": "7750",
        "deleted_at": "2025-03-24 22:15:35"
    },
    {
        "id": 70,
        "name": "김미영",
        "present": false,
        "code": "",
        "timestamp": null,
        "password": "7555",
        "deleted_at": "2025-03-24 22:15:35"
    },
    {
        "id": 71,
        "name": "김민국",
        "present": false,
        "code": "",
        "timestamp": null,
        "password": "4442",
        "deleted_at": "2025-03-24 22:15:35"
    },
    {
        "id": 76,
        "name": "김유림",
        "present": false,
        "code": "",
        "timestamp": null,
        "password": "9889",
        "deleted_at": "2025-03-24 22:15:35"
    },
    {
        "id": 78,
        "name": "김지훈",
        "present": false,
        "code": "",
        "timestamp": null,
        "password": "2865",
        "deleted_at": "2025-03-24 22:15:35"
    },
    {
        "id": 81,
        "name": "남궁시윤",
        "present": false,
        "code": "",
        "timestamp": null,
        "password": "5689",
        "deleted_at": "2025-03-24 22:15:35"
    },
    {
        "id": 82,
        "name": "문지원",
        "present": false,
        "code": "",
        "timestamp": null,
        "password": "5673",
        "deleted_at": "2025-03-24 22:15:35"
    },
    {
        "id": 85,
        "name": "박지영",
        "present": false,
        "code": "",
        "timestamp": null,
        "password": "9668",
        "deleted_at": "2025-03-24 22:15:35"
    },
    {
        "id": 86,
        "name": "박하연",
        "present": false,
        "code": "",
        "timestamp": null,
        "password": "0505",
        "deleted_at": "2025-03-24 22:15:35"
    },
    {
        "id": 89,
        "name": "송수민",
        "present": false,
        "code": "",
        "timestamp": null,
        "password": "8880",
        "deleted_at": "2025-03-24 22:15:35"
    },
    {
        "id": 92,
        "name": "오주희",
        "present": false,
        "code": "",
        "timestamp": null,
        "password": "3830",
        "deleted_at": "2025-03-24 22:15:35"
    },
    {
        "id": 97,
        "name": "이경찬",
        "present": false,
        "code": "",
        "timestamp": null,
        "password": "5570",
        "deleted_at": "2025-03-24 22:15:35"
    },
    {
        "id": 104,
        "name": "전은규",
        "present": false,
        "code": "",
        "timestamp": null,
        "password": "4366",
        "deleted_at": "2025-03-24 22:15:35"
    },
    {
        "id": 105,
        "name": "전종민",
        "present": false,
        "code": "",
        "timestamp": null,
        "password": "3351",
        "deleted_at": "2025-03-24 22:15:35"
    },
    {
        "id": 109,
        "name": "지중헌",
        "present": false,
        "code": "",
        "timestamp": null,
        "password": "3020",
        "deleted_at": "2025-03-24 22:15:35"
    }
]